README.md
setup.py
chessplot/__init__.py
chessplot/chessplot.py
chessplot/interpreter.py
chessplot/parser.py
chessplot/piece.py
chessplot/ply.py
chessplot/position.py
chessplot/settings.py
chessplot.egg-info/PKG-INFO
chessplot.egg-info/SOURCES.txt
chessplot.egg-info/dependency_links.txt
chessplot.egg-info/requires.txt
chessplot.egg-info/top_level.txt